<PAMDataset>
  <PAMRasterBand band="1">
    <Histograms>
      <HistItem>
        <HistMin>0.01234567910432816</HistMin>
        <HistMax>1</HistMax>
        <BucketCount>256</BucketCount>
        <IncludeOutOfRange>1</IncludeOutOfRange>
        <Approximate>0</Approximate>
        <HistCounts>131|0|0|80|0|0|102|0|0|65|0|0|87|0|0|78|0|0|0|66|0|0|75|0|0|84|0|0|64|0|0|80|0|0|0|66|0|0|68|0|0|61|0|0|60|0|0|57|0|0|0|71|0|0|77|0|0|74|0|0|67|0|0|66|0|0|75|0|0|0|67|0|0|87|0|0|77|0|0|83|0|0|101|0|0|0|85|0|0|75|0|0|77|0|0|72|0|0|83|0|0|0|80|0|0|92|0|0|74|0|0|93|0|0|106|0|0|101|0|0|0|98|0|0|85|0|0|87|0|0|102|0|0|82|0|0|0|99|0|0|103|0|0|111|0|0|106|0|0|88|0|0|0|104|0|0|98|0|0|111|0|0|125|0|0|120|0|0|98|0|0|0|114|0|0|119|0|0|121|0|0|129|0|0|127|0|0|0|158|0|0|139|0|0|154|0|0|160|0|0|160|0|0|0|159|0|0|167|0|0|181|0|0|176|0|0|203|0|0|234|0|0|0|270|0|0|353|0|0|314|0|0|335|0|0|401|0|0|0|435|0|0|493|0|0|520|0|0|580|0|0|534|0|0|0|11700</HistCounts>
      </HistItem>
    </Histograms>
    <Metadata>
      <MDI key="RepresentationType">ATHEMATIC</MDI>
      <MDI key="STATISTICS_COVARIANCES">0.06972788180980788</MDI>
      <MDI key="STATISTICS_EXCLUDEDVALUES"></MDI>
      <MDI key="STATISTICS_MAXIMUM">1</MDI>
      <MDI key="STATISTICS_MEAN">0.83724155041865</MDI>
      <MDI key="STATISTICS_MINIMUM">0.012345679104328</MDI>
      <MDI key="STATISTICS_SKIPFACTORX">1</MDI>
      <MDI key="STATISTICS_SKIPFACTORY">1</MDI>
      <MDI key="STATISTICS_STDDEV">0.2640603753118</MDI>
    </Metadata>
  </PAMRasterBand>
</PAMDataset>
